<form xmlns:xsi="http://www.w3.org/2001/XMLSchema-instance"
  xsi:noNamespaceSchemaLocation="urn:magento:module:Magento_Ui:etc/ui_configuration.xsd">
    <fieldset name="mycustomtab">
        <argument name="data" xsi:type="array">
            <item name="config" xsi:type="array">
                <item name="label" xsi:type="string" translate="true">My Custom Tab</item>
                <item name="provider" xsi:type="string">product</item>
                <item name="sortOrder" xsi:type="number">150</item>
                <item name="collapsible" xsi:type="boolean">true</item>
                <item name="opened" xsi:type="boolean">false</item>
                <item name="ns" xsi:type="string">product_form</item>
            </item>
        </argument>
        <field name="my_custom_attribute">
            <argument name="data" xsi:type="array">
                <item name="config" xsi:type="array">
                    <item name="sortOrder" xsi:type="number">10</item>
                    <item name="dataType" xsi:type="string">int</item>
                    <item name="formElement" xsi:type="string">input</item>
                    <item name="label" xsi:type="string" translate="true">My Custom Attribute</item>
                </item>
            </argument>
        </field>
    </fieldset>
</form>